<?xml version="1.0" encoding="UTF-8" standalone="yes"?>
<photographer xmlns="http://www.example.org/photoBay" ref="./photographers/1" ID="1" photosRef="./photographers/1/photos" photoSellsRef="./photographers/1/photoSells">
    <firstname>David</firstname>
    <lastname>Wachs</lastname>
    <birthdate>1990-04-01Z</birthdate>
    <sex>m</sex>
    <equipment></equipment>
    <generalPersonalData>
        <address>
            <street>Am Rosengarten</street>
            <houseNumber>13</houseNumber>
            <postalCode>50170</postalCode>
            <city>Kerpen</city>
            <country>Germany</country>
        </address>
        <username>dwachs</username>
        <email>davidwachs@hotmail.de</email>
        <phone></phone>
        <description></description>
        <website></website>
    </generalPersonalData>
</photographer>
